hangar_api/__init__.py
hangar_api/api_client.py
hangar_api/api_response.py
hangar_api/configuration.py
hangar_api/exceptions.py
hangar_api/py.typed
hangar_api/rest.py
hangar_api/api/__init__.py
hangar_api/api/api_keys_api.py
hangar_api/api/authentication_api.py
hangar_api/api/pages_api.py
hangar_api/api/permissions_api.py
hangar_api/api/projects_api.py
hangar_api/api/users_api.py
hangar_api/api/versions_api.py
hangar_api/models/__init__.py
hangar_api/models/api_key.py
hangar_api/models/api_session.py
hangar_api/models/category.py
hangar_api/models/channel_flag.py
hangar_api/models/color.py
hangar_api/models/compact_role.py
hangar_api/models/create_api_key_form.py
hangar_api/models/day_project_stats.py
hangar_api/models/file_info.py
hangar_api/models/link.py
hangar_api/models/link_section.py
hangar_api/models/multipart_file_or_url.py
hangar_api/models/named_permission.py
hangar_api/models/page_edit_form.py
hangar_api/models/paginated_result_project.py
hangar_api/models/paginated_result_project_compact.py
hangar_api/models/paginated_result_project_member.py
hangar_api/models/paginated_result_user.py
hangar_api/models/paginated_result_version.py
hangar_api/models/pagination.py
hangar_api/models/permission_check.py
hangar_api/models/permission_type.py
hangar_api/models/pinned_status.py
hangar_api/models/platform.py
hangar_api/models/platform_version_download.py
hangar_api/models/plugin_dependency.py
hangar_api/models/project.py
hangar_api/models/project_channel.py
hangar_api/models/project_compact.py
hangar_api/models/project_donation_settings.py
hangar_api/models/project_license.py
hangar_api/models/project_member.py
hangar_api/models/project_namespace.py
hangar_api/models/project_settings.py
hangar_api/models/project_sorting_strategy.py
hangar_api/models/project_stats.py
hangar_api/models/request_pagination.py
hangar_api/models/review_state.py
hangar_api/models/string_content.py
hangar_api/models/uploaded_version.py
hangar_api/models/user.py
hangar_api-2023.12.dist-info/METADATA
hangar_api-2023.12.dist-info/WHEEL
hangar_api-2023.12.dist-info/top_level.txt
hangar_api-2023.12.dist-info/RECORD
